admin_jqueryui
