Metadata-Version: 1.1
Name: django-admin-jqueryui
Version: 1.8.22
Summary: Simply adds a jquery ui to the admin panel
Home-page: https://github.com/hint/django-admin-jqueryui
Author: Piotr Kilczuk -- Hint
Author-email: piotr@hint.pl
License: UNKNOWN
Platform: UNKNOWN
Classifier: Framework :: Django
Classifier: Environment :: Web Environment
Classifier: Programming Language :: Python
Classifier: Intended Audience :: Developers
Classifier: Operating System :: OS Independent
Classifier: License :: OSI Approved :: BSD License
Classifier: Topic :: Software Development :: Libraries :: Python Modules
Provides: admin_jqueryui
